npm_analyser/__init__.py
npm_analyser/npm_analyser.py
npm_analyser-1.0.0.dist-info/LICENSE
npm_analyser-1.0.0.dist-info/METADATA
npm_analyser-1.0.0.dist-info/WHEEL
npm_analyser-1.0.0.dist-info/top_level.txt
npm_analyser-1.0.0.dist-info/RECORD
