Metadata-Version: 2.1
Name: npm-analyser
Version: 1.0.0
Summary: A Python library to monitor an npm package!
Home-page: https://github.com/iampukar/npm_analyser
Author: Pukar Acharya
License: UNKNOWN
Project-URL: Bug Tracker, https://github.com/iampukar/npm_analyser/issues
Platform: UNKNOWN
Classifier: Programming Language :: Python :: 3
Classifier: License :: OSI Approved :: MIT License
Requires-Python: >=3.9.7
License-File: LICENSE
